augly/__init__.py
augly/assets/audio/silent.flac
augly/assets/fonts/AlexBrush-Regular.pkl
augly/assets/fonts/AlexBrush-Regular.ttf
augly/assets/fonts/Allura-Regular.pkl
augly/assets/fonts/Allura-Regular.ttf
augly/assets/fonts/CaviarDreams.pkl
augly/assets/fonts/CaviarDreams.ttf
augly/assets/fonts/CaviarDreams_BoldItalic.pkl
augly/assets/fonts/CaviarDreams_BoldItalic.ttf
augly/assets/fonts/CaviarDreams_Italic.pkl
augly/assets/fonts/CaviarDreams_Italic.ttf
augly/assets/fonts/Caviar_Dreams_Bold.pkl
augly/assets/fonts/Caviar_Dreams_Bold.ttf
augly/assets/fonts/Chunkfive.pkl
augly/assets/fonts/Chunkfive.ttf
augly/assets/fonts/DancingScript-Regular.pkl
augly/assets/fonts/DancingScript-Regular.ttf
augly/assets/fonts/DavysDingbats.pkl
augly/assets/fonts/DavysDingbats.ttf
augly/assets/fonts/Elsie-Black.pkl
augly/assets/fonts/Elsie-Black.ttf
augly/assets/fonts/Elsie-Regular.pkl
augly/assets/fonts/Elsie-Regular.ttf
augly/assets/fonts/ElsieSwashCaps-Black.pkl
augly/assets/fonts/ElsieSwashCaps-Black.ttf
augly/assets/fonts/ElsieSwashCaps-Regular.pkl
augly/assets/fonts/ElsieSwashCaps-Regular.ttf
augly/assets/fonts/Entypo.pkl
augly/assets/fonts/Entypo.ttf
augly/assets/fonts/GrandHotel-Regular.pkl
augly/assets/fonts/GrandHotel-Regular.ttf
augly/assets/fonts/GreatVibes-Regular.pkl
augly/assets/fonts/GreatVibes-Regular.ttf
augly/assets/fonts/IBMPlexMono-Bold.pkl
augly/assets/fonts/IBMPlexMono-Bold.ttf
augly/assets/fonts/IBMPlexMono-BoldItalic.pkl
augly/assets/fonts/IBMPlexMono-BoldItalic.ttf
augly/assets/fonts/IBMPlexMono-ExtraLight.pkl
augly/assets/fonts/IBMPlexMono-ExtraLight.ttf
augly/assets/fonts/IBMPlexMono-ExtraLightItalic.pkl
augly/assets/fonts/IBMPlexMono-ExtraLightItalic.ttf
augly/assets/fonts/IBMPlexMono-Italic.pkl
augly/assets/fonts/IBMPlexMono-Italic.ttf
augly/assets/fonts/IBMPlexMono-Light.pkl
augly/assets/fonts/IBMPlexMono-Light.ttf
augly/assets/fonts/IBMPlexMono-LightItalic.pkl
augly/assets/fonts/IBMPlexMono-LightItalic.ttf
augly/assets/fonts/IBMPlexMono-Medium.pkl
augly-1.0.0.dist-info/LICENSE
augly-1.0.0.dist-info/METADATA
augly-1.0.0.dist-info/WHEEL
augly-1.0.0.dist-info/top_level.txt
augly-1.0.0.dist-info/RECORD
