Metadata-Version: 2.1
Name: augly
Version: 1.0.0
Summary: A data augmentations library for audio, image, text, & video.
Home-page: https://github.com/facebookresearch/AugLy
Author: Zoe Papakipos and Joanna Bitton
Author-email: zoep@fb.com
License: UNKNOWN
Platform: UNKNOWN
Classifier: Programming Language :: Python :: 3
Classifier: License :: OSI Approved :: MIT License
Classifier: Operating System :: OS Independent
Requires-Python: >=3.6
License-File: LICENSE
Requires-Dist: iopath (>=0.1.8)
Requires-Dist: python-magic (>=0.4.22)
Requires-Dist: regex (>=2021.4.4)
Provides-Extra: all
Requires-Dist: numpy (>=1.19.5) ; extra == 'all'
Requires-Dist: audioread (>=2.1.9) ; extra == 'all'
Requires-Dist: nlpaug (==1.1.3) ; extra == 'all'
Requires-Dist: torch (>=1.9.0) ; extra == 'all'
Requires-Dist: librosa (>=0.8.1) ; extra == 'all'
Requires-Dist: vidgear (>=0.2.4) ; extra == 'all'
Requires-Dist: SoundFile (>=0.10.3.post1) ; extra == 'all'
Requires-Dist: torchaudio (>=0.9.0) ; extra == 'all'
Requires-Dist: Pillow (<9.0.0,>=8.2.0) ; extra == 'all'
Requires-Dist: opencv-python (>=4.5.2.54) ; extra == 'all'
Requires-Dist: ffmpeg-python (>=0.2.0) ; extra == 'all'
Provides-Extra: audio
Requires-Dist: audioread (>=2.1.9) ; extra == 'audio'
Requires-Dist: librosa (>=0.8.1) ; extra == 'audio'
Requires-Dist: numpy (>=1.19.5) ; extra == 'audio'
Requires-Dist: SoundFile (>=0.10.3.post1) ; extra == 'audio'
Requires-Dist: torch (>=1.9.0) ; extra == 'audio'
Requires-Dist: torchaudio (>=0.9.0) ; extra == 'audio'
Provides-Extra: image
Requires-Dist: numpy (>=1.19.5) ; extra == 'image'
Requires-Dist: Pillow (<9.0.0,>=8.2.0) ; extra == 'image'
Requires-Dist: torch (>=1.9.0) ; extra == 'image'
Provides-Extra: text
Requires-Dist: nlpaug (==1.1.3) ; extra == 'text'
Provides-Extra: video
Requires-Dist: ffmpeg-python (>=0.2.0) ; extra == 'video'
Requires-Dist: numpy (>=1.19.5) ; extra == 'video'
Requires-Dist: opencv-python (>=4.5.2.54) ; extra == 'video'
Requires-Dist: Pillow (<9.0.0,>=8.2.0) ; extra == 'video'
Requires-Dist: vidgear (>=0.2.4) ; extra == 'video'
Requires-Dist: audioread (>=2.1.9) ; extra == 'video'
Requires-Dist: librosa (>=0.8.1) ; extra == 'video'
Requires-Dist: SoundFile (>=0.10.3.post1) ; extra == 'video'
Requires-Dist: torch (>=1.9.0) ; extra == 'video'
Requires-Dist: torchaudio (>=0.9.0) ; extra == 'video'
